{
  "category": "drinks",
  "price_thb": 85,
  "name": {
    "en": "Oat milk latte",
    "th": "ลาเต้นมข้าวโอ๊ต",
    "ru": "Латте на овсяном молоке"
  },
  "description": {
    "en": "Double espresso with our house-made oat milk. Also available iced.",
    "th": "เอสเพรสโซ่ช็อตคู่กับนมข้าวโอ๊ตโฮมเมด สั่งเย็นได้",
    "ru": "Двойной эспрессо с домашним овсяным молоком. Есть и холодный вариант."
  },
  "slug": {
    "en": "oat-milk-latte",
    "th": "ลาเต้นมข้าวโอ๊ต",
    "ru": "latte-na-ovsyanom-moloke"
  },
  "previousSlugs": [],
  "images": [],
  "dietaryTags": ["vegan", "jay"],
  "allergens": ["gluten"],
  "spicyLevel": 0,
  "available": true,
  "featured": false,
  "source": "retyped",
  "reviewedAt": null
}
